Validly/__init__.py
Validly/validator.py
validly-1.0.22.dist-info/licenses/LICENSE
validly-1.0.22.dist-info/METADATA
validly-1.0.22.dist-info/WHEEL
validly-1.0.22.dist-info/top_level.txt
validly-1.0.22.dist-info/RECORD
